{"Exercises":[{"ID_Exercise":500,"Description":"Х-stop. Забивать прицельный шар и оставлять биток на месте (допускается движение битка вперед-назад, вправо-влево не более одного мелка от позиции «стопа»).","Target":4,"CntOfRepeat":14,"RelToGroup":[{"ID_Group":1,"RelToSuperGroup":[{"ID_SuperGroup":12}]}]},{"ID_Exercise":501,"Description":"Забить все 15 шаров. Биток перед каждым ударом ставить на небольшую резку, примерно два шара в бок. обращать внимание на качество удара","Target":15,"CntOfRepeat":3,"RelToGroup":[{"ID_Group":1,"RelToSuperGroup":[{"ID_SuperGroup":12}]}]},{"ID_Exercise":502,"Description":"Забить шар в мелке от борта. биток перпендикулярно перевести на противоположный борт","Target":2,"CntOfRepeat":15,"RelToGroup":[{"ID_Group":1,"RelToSuperGroup":[{"ID_SuperGroup":12}]}]},{"ID_Exercise":503,"Description":"Забивать шары :)  обращать внимание на КАЧЕСТВО и РАЗМЕР удара","Target":2,"CntOfRepeat":30,"RelToGroup":[{"ID_Group":1,"RelToSuperGroup":[{"ID_SuperGroup":12}]}]}]}
